nonlinear_clock/__init__.py
nonlinear_clock/graph.py
nonlinear_clock/plot.py
nonlinear_clock-0.0.1.dist-info/LICENSE
nonlinear_clock-0.0.1.dist-info/METADATA
nonlinear_clock-0.0.1.dist-info/WHEEL
nonlinear_clock-0.0.1.dist-info/top_level.txt
nonlinear_clock-0.0.1.dist-info/RECORD
